optionsStrategies/__init__.py
optionsStrategies/strategies.py
optionsStrategies-0.1.1.dist-info/METADATA
optionsStrategies-0.1.1.dist-info/WHEEL
optionsStrategies-0.1.1.dist-info/top_level.txt
optionsStrategies-0.1.1.dist-info/RECORD
