Metadata-Version: 2.1
Name: optionsStrategies
Version: 0.1.1
Summary: Options Strategies library
Home-page: UNKNOWN
Author: Pulkit Gupta| https://www.linkedin.com/in/pulkitgupta31/
Author-email: <iampulkit31@gmail.com>
License: UNKNOWN
Keywords: options,strategies,payoff,profit,loss
Platform: UNKNOWN
Requires-Dist: scipy
